{"nodes": [{"id": "src_components_sw_register", "label": "Service Worker Register (PWA)", "file_type": "code", "source_file": "src/components/sw-register.tsx", "source_location": null, "source_url": null, "captured_at": null, "author": null, "contributor": null}], "edges": [{"source": "src_components_sw_register", "target": "src_lib_rate_limit", "relation": "conceptually_related_to", "confidence": "AMBIGUOUS", "confidence_score": 0.2, "source_file": "src/components/sw-register.tsx", "source_location": 25, "weight": 0.2}], "hyperedges": []}